cmo_gymnasium/__init__.py
cmo_gymnasium/builder.py
cmo_gymnasium/world.py
cmo_gymnasium/agents/__init__.py
cmo_gymnasium/agents/ant.py
cmo_gymnasium/agents/car.py
cmo_gymnasium/agents/doggo.py
cmo_gymnasium/agents/point.py
cmo_gymnasium/agents/racecar.py
cmo_gymnasium/assets/__init__.py
cmo_gymnasium/assets/color.py
cmo_gymnasium/assets/group.py
cmo_gymnasium/assets/robot.py
cmo_gymnasium/assets/free_geoms/__init__.py
cmo_gymnasium/assets/free_geoms/push_box.py
cmo_gymnasium/assets/free_geoms/vases.py
cmo_gymnasium/assets/geoms/__init__.py
cmo_gymnasium/assets/geoms/apples.py
cmo_gymnasium/assets/geoms/buttons.py
cmo_gymnasium/assets/geoms/circle.py
cmo_gymnasium/assets/geoms/goal.py
cmo_gymnasium/assets/geoms/hazards.py
cmo_gymnasium/assets/geoms/oranges.py
cmo_gymnasium/assets/geoms/pillars.py
cmo_gymnasium/assets/geoms/sigwalls.py
cmo_gymnasium/assets/geoms/walls.py
cmo_gymnasium/assets/meshes/bamboo_wall.obj
cmo_gymnasium/assets/meshes/bush.obj
cmo_gymnasium/assets/meshes/chassis_differential.STL
cmo_gymnasium/assets/meshes/cliff1.obj
cmo_gymnasium/assets/meshes/cliff2.obj
cmo_gymnasium/assets/meshes/cliff3.obj
cmo_gymnasium/assets/meshes/diff_carrier.stl
cmo_gymnasium/assets/meshes/diff_ring.stl
cmo_gymnasium/assets/meshes/diff_side.stl
cmo_gymnasium/assets/meshes/diff_spider.stl
cmo_gymnasium/assets/meshes/flower_bush.obj
cmo_gymnasium/assets/meshes/left_front_wheel.obj
cmo_gymnasium/assets/meshes/left_rear_wheel.obj
cmo_gymnasium/assets/meshes/left_steering_hinge.STL
cmo_gymnasium/assets/meshes/right_front_wheel.obj
cmo_gymnasium/assets/meshes/right_rear_wheel.obj
cmo_gymnasium/assets/meshes/right_steering_hinge.STL
cmo_gymnasium/assets/meshes/wooden_door1.obj
cmo_gymnasium/assets/mocaps/__init__.py
cmo_gymnasium/assets/mocaps/gremlins.py
cmo_gymnasium/assets/textures/star_hd.back.png
cmo_gymnasium/assets/textures/star_hd.bottom.png
cmo_gymnasium/assets/textures/star_hd.front.png
cmo_gymnasium/assets/textures/star_hd.left.png
cmo_gymnasium-1.0.0.dist-info/METADATA
cmo_gymnasium-1.0.0.dist-info/WHEEL
cmo_gymnasium-1.0.0.dist-info/top_level.txt
cmo_gymnasium-1.0.0.dist-info/RECORD
