Metadata-Version: 2.1
Name: cmo_gymnasium
Version: 1.0.0
Requires-Python: >=3.9
Requires-Dist: gymnasium==0.28.1
Requires-Dist: pygame==2.1.3
Requires-Dist: mujoco==2.3.3
Requires-Dist: xmltodict>=0.13.0
Requires-Dist: pyyaml>=6.0
Requires-Dist: imageio>=2.27.0
Requires-Dist: gymnasium-robotics<1.3.0,>=1.2.0
Requires-Dist: scipy>=1.7.0
Requires-Dist: gymnasium[box2d]==0.28.1
